{"changelog.md":"DLsnj7SG","docs_about_changelog.md":"NSEmZefO","docs_about_team.md":"CGMaHtLp","docs_documents_account.md":"5GCPta3F","docs_documents_customization.md":"DFHMmX_V","docs_documents_index.md":"CKPuMcdp","docs_documents_plugin_market.md":"BIqwQURW","docs_documents_start.md":"nMXv2Kd5","docs_documents_sync.md":"BVfF5Bl2","docs_hello.md":"DCFuBWQ-","docs_plugin-extensions_readme.md":"DVQKdycj","docs_plugin-extensions_search-sorting-api.md":"TUWVspV5","docs_plugins_api_event.md":"DMOZ-2lj","docs_plugins_config_init.md":"BN6NS8bK","docs_plugins_config_manifest.md":"CJ2I7uJ8","docs_plugins_events.md":"D6yo0I7J","docs_plugins_feature_examples.md":"LwtU6rBu","docs_plugins_feature_index.md":"C714GkL2","docs_plugins_feature_overview.md":"BsGcuE89","docs_plugins_i18n.md":"8KQr_RcG","docs_plugins_introduction.md":"DsXdp13z","docs_plugins_permission.md":"CDLdvQbC","docs_plugins_preloadjs.md":"Cj0LmJR0","docs_plugins_publish.md":"CfJXSIZX","docs_plugins_setup.md":"DITecxTV","docs_plugins_snippets.md":"BTxpQFc8","docs_plugins_storage.md":"BBgcZ8qd","docs_plugins_theme.md":"BKREJFRy","docs_plugins_toast.md":"Bl05In4x","docs_plugins_utils.md":"HSKsTX47","docs_plugins_widget.md":"B6t2bLoI","docs_q-a_index.md":"R-TeMswy","index.md":"CJq3xboU","readme.md":"BaT2BJZe"}
